idem_tls/conf.py
idem_tls/version.py
idem_tls/acct/tls/init.py
idem_tls/exec/tls/certificate.py
idem_tls/exec/tls/init.py
idem_tls/states/tls/init.py
idem_tls/tool/tls/certificate.py
idem_tls-2.0.0.dist-info/LICENSE
idem_tls-2.0.0.dist-info/METADATA
idem_tls-2.0.0.dist-info/WHEEL
idem_tls-2.0.0.dist-info/entry_points.txt
idem_tls-2.0.0.dist-info/top_level.txt
idem_tls-2.0.0.dist-info/RECORD
