Metadata-Version: 2.1
Name: idem-tls
Version: 2.0.0
Summary: UNKNOWN
Home-page: UNKNOWN
Author: Barnali Rakshit
Author-email: brakshit@vmware.com
License: UNKNOWN
Platform: UNKNOWN
Classifier: Environment :: Console
Classifier: Intended Audience :: Developers
Classifier: Intended Audience :: Information Technology
Classifier: Intended Audience :: System Administrators
Classifier: Operating System :: OS Independent
Classifier: Programming Language :: Python
Classifier: Programming Language :: Python :: 3.8
Classifier: Programming Language :: Python :: 3.9
Classifier: Programming Language :: Python :: 3.10
Classifier: Programming Language :: Python :: 3.11
Classifier: Development Status :: 5 - Production/Stable
Requires-Python: >=3.8
License-File: LICENSE
Requires-Dist: pop (>=23.0.0)
Requires-Dist: idem (>=23.0.0)
Requires-Dist: PyYaml (>=6.0.1)
Requires-Dist: cryptography (<42.0.0,>=40.0.0)
Requires-Dist: pyopenssl (>=23.0.0)
